keyslide/__init__.py
keyslide/main.py
keyslide-0.7.dist-info/METADATA
keyslide-0.7.dist-info/WHEEL
keyslide-0.7.dist-info/entry_points.txt
keyslide-0.7.dist-info/top_level.txt
keyslide-0.7.dist-info/RECORD
