Metadata-Version: 2.1
Name: keyslide
Version: 0.7
Summary: Encrypt text by shifting keys on the QWERTY keyboard.
